CHANGELOG.md
MANIFEST.in
README.md
setup.cfg
setup.py
pip_services3_sqlserver/__init__.py
pip_services3_sqlserver.egg-info/PKG-INFO
pip_services3_sqlserver.egg-info/SOURCES.txt
pip_services3_sqlserver.egg-info/dependency_links.txt
pip_services3_sqlserver.egg-info/requires.txt
pip_services3_sqlserver.egg-info/top_level.txt
pip_services3_sqlserver.egg-info/zip-safe
pip_services3_sqlserver/build/DefaultSqlServerFactory.py
pip_services3_sqlserver/build/__init__.py
pip_services3_sqlserver/connect/SqlServerConnection.py
pip_services3_sqlserver/connect/SqlServerConnectionResolver.py
pip_services3_sqlserver/connect/__init__.py
pip_services3_sqlserver/persistence/IdentifiableJsonSqlServerPersistence.py
pip_services3_sqlserver/persistence/IdentifiableSqlServerPersistence.py
pip_services3_sqlserver/persistence/SqlServerPersistence.py
pip_services3_sqlserver/persistence/__init__.py
test/connect/__init__.py
test/connect/test_DummySqlServerConnection.py
test/connect/test_SqlServerConnection.py
test/connect/test_SqlServerConnectionResolver.py
test/fixtures/Dummy.py
test/fixtures/DummyPersistenceFixture.py
test/fixtures/IDummyPersistence.py
test/fixtures/__init__.py
test/persistence/DummyJsonSqlServerPersistence.py
test/persistence/DummySqlServerPersistence.py
test/persistence/__init__.py
test/persistence/test_DummyJsonSqlServerPersistence.py
test/persistence/test_DummySqlServerPersistence.py